[{"line":1,"elements":[{"start_timestamp":"2025-05-04T14:03:25.714Z","line":14,"name":"Verify if place is being addes successfully using Add place Api","description":"","id":"validating-place-api-s;verify-if-place-is-being-addes-successfully-using-add-place-api;;2","type":"scenario","keyword":"Scenario Outline","steps":[{"result":{"duration":689114300,"status":"passed"},"line":5,"name":"Add place payload \"Rak\" \"<language>\" \"Bengaluru\"","match":{"arguments":[{"val":"\"Rak\"","offset":18},{"val":"\"<language>\"","offset":24},{"val":"\"Bengaluru\"","offset":37}],"location":"stepDefinition.stepdefinitions.add_place_payload(java.lang.String,java.lang.String,java.lang.String)"},"keyword":"Given "},{"result":{"duration":940198100,"status":"passed"},"line":6,"name":"user calls \"AddplaceAPI\" with \"POST\" http request","match":{"arguments":[{"val":"\"AddplaceAPI\"","offset":11},{"val":"\"POST\"","offset":30}],"location":"stepDefinition.stepdefinitions.user_calls_with_post_http_request(java.lang.String,java.lang.String)"},"keyword":"When "},{"result":{"duration":1000000,"status":"passed"},"line":7,"name":"the API call is success with status code 200","match":{"arguments":[{"val":"200","offset":41}],"location":"stepDefinition.stepdefinitions.the_api_call_is_success_with_status_code(java.lang.Integer)"},"keyword":"Then "},{"result":{"duration":357463800,"status":"passed"},"line":8,"name":"\"status\" in response body is \"OK\"","match":{"arguments":[{"val":"\"status\"","offset":0},{"val":"\"OK\"","offset":29}],"location":"stepDefinition.stepdefinitions.in_response_body_is(java.lang.String,java.lang.String)"},"keyword":"And "},{"result":{"duration":10005700,"status":"passed"},"line":9,"name":"\"scope\" in response body is \"APP\"","match":{"arguments":[{"val":"\"scope\"","offset":0},{"val":"\"APP\"","offset":28}],"location":"stepDefinition.stepdefinitions.in_response_body_is(java.lang.String,java.lang.String)"},"keyword":"And "},{"result":{"duration":1314917200,"status":"passed"},"line":10,"name":"Verify place_id created maps to \"Rak\" using \"getPlaceAPI\"","match":{"arguments":[{"val":"\"Rak\"","offset":32},{"val":"\"getPlaceAPI\"","offset":44}],"location":"stepDefinition.stepdefinitions.verify_place_id_created_maps_to_using(java.lang.String,java.lang.String)"},"keyword":"And "}],"tags":[{"name":"@AddPlace"},{"name":"@Regression"}]},{"start_timestamp":"2025-05-04T14:03:29.038Z","line":17,"name":"Verify if delete place functionality is working fine","description":"","id":"validating-place-api-s;verify-if-delete-place-functionality-is-working-fine","type":"scenario","keyword":"Scenario","steps":[{"result":{"duration":1002700,"status":"passed"},"line":18,"name":"DeletePlacePayload","match":{"location":"stepDefinition.stepdefinitions.delete_place_payload()"},"keyword":"Given "},{"result":{"duration":1869907700,"status":"passed"},"line":19,"name":"user calls \"deletePlaceAPI\" with \"POST\" http request","match":{"arguments":[{"val":"\"deletePlaceAPI\"","offset":11},{"val":"\"POST\"","offset":33}],"location":"stepDefinition.stepdefinitions.user_calls_with_post_http_request(java.lang.String,java.lang.String)"},"keyword":"When "},{"result":{"status":"passed"},"line":20,"name":"the API call is success with status code 200","match":{"arguments":[{"val":"200","offset":41}],"location":"stepDefinition.stepdefinitions.the_api_call_is_success_with_status_code(java.lang.Integer)"},"keyword":"Then "},{"result":{"duration":9937600,"status":"passed"},"line":21,"name":"\"status\" in response body is \"OK\"","match":{"arguments":[{"val":"\"status\"","offset":0},{"val":"\"OK\"","offset":29}],"location":"stepDefinition.stepdefinitions.in_response_body_is(java.lang.String,java.lang.String)"},"keyword":"And "}],"tags":[{"name":"@DeletePlace"},{"name":"@Regression"}]}],"name":"Validating Place API's","description":"","id":"validating-place-api-s","keyword":"Feature","uri":"file:src/test/java/feature/placeValidation.feature","tags":[]}]